languagemodels/__init__.py
languagemodels/config.py
languagemodels/embeddings.py
languagemodels/inference.py
languagemodels/models.py
languagemodels-0.23.0.dist-info/METADATA
languagemodels-0.23.0.dist-info/WHEEL
languagemodels-0.23.0.dist-info/top_level.txt
languagemodels-0.23.0.dist-info/RECORD
